[{"email":"1tgh","message":"1tgh","name":"1tgh","subject":"1tgh"},{"email":"2tgh","message ":"2tgh","name":"2tgh","subject":"2tgh"},{"email":"","message":"yteuetyue","name":"tyuetyuetyuety","subject":"etyuetyuety"},{"email":"","message":"uyiyuiryuiryu yu ryiu iryu iryu","name":"iryuiryuiryu","subject":"uiryui"},{"email":"","message":"tyueytuetyuetyue","name":" tyu etyu ety uety utye","subject":"tyuetyuetyu"},{"email":"","message":"","name":"","subject":""},{"email":"","message":"etyuety","name":"","subject":""},{"email":"","message":"","name":"","subject":""},{"email":"","message":"","name":"","subject":""},{"email":"","message":"5675673567","name":"","subject":""},{"email":"","message":"","name":"","subject":""},{"email":"","message":"","name":"","subject":""},{"email":"u ety uety ue","message":"urtyuetyu","name":"etyu ety","subject":"ty uety uety uety"},{"email":"uiryui","message":"7iryuiryuir","name":"ruyuiry","subject":"yuiryuiryuiryuiryu"},{"email":"","message":"jhgjhkfkfhjkfhjfkjfhjkfhjkfhj fhjk fui y jhgjhkfkfhjkfhjfkjfhjkfhjkfhj fhjk fui y ","name":"hj kfhjk fhjk fj kfhjk fhjkf hjk fhjk","subject":"jhk hfj kfhjk jh k"},{"email":"","message":"467847846m78 67 84678 467","name":"67846784678","subject":"4678467846"},{"email":"","message":"76","name":"","subject":""},{"email":"","message":"","name":"","subject":""},{"email":"","message":"476","name":"","subject":""},{"email":"","message":"678467846784","name":"","subject":""},{"email":"","message":"","name":"","subject":""},{"email":"","message":"r67867,867 867 8e678 e67 8678","name":"67 867 8","subject":""},{"email":"","message":"ueuty","name":"","subject":""},{"email":"rtutr@yhejhetyjt.yrfuk","message":"etyuety","name":"uety","subject":"tyu ety"},{"email":"","message":"111111111111111111111111","name":"11111111","subject":"111111111111111111111111"},{"email":"","message":"","name":"","subject":""},{"email":"","message":"","name":"","subject":""},{"email":"hklhl","message":"h","name":"456345","subject":"njh"}]